shuffled/__init__.py
shuffled/core.py
shuffled/crypto.py
shuffled/feistel.py
shuffled/py.typed
shuffled-1.1.0.dist-info/METADATA
shuffled-1.1.0.dist-info/LICENSE
shuffled-1.1.0.dist-info/WHEEL
shuffled-1.1.0.dist-info/RECORD
