Metadata-Version: 2.1
Name: shuffled
Version: 1.1.0
Summary: Iterate randomly over integer ranges
Home-page: https://github.com/bbc2/shuffled
License: MIT
Keywords: random,integer,iterator
Author: Bertrand Bonnefoy-Claudet
Author-email: bertrand@bertrandbc.com
Requires-Python: >=3.7,<4.0
Classifier: Intended Audience :: Developers
Classifier: License :: OSI Approved :: MIT License
Classifier: Programming Language :: Python :: 3
Classifier: Programming Language :: Python :: 3.7
Classifier: Programming Language :: Python :: 3.8
Classifier: Programming Language :: Python :: 3.9
Classifier: Programming Language :: Python :: 3.10
Classifier: Programming Language :: Python :: 3.11
Classifier: Programming Language :: Python :: Implementation :: CPython
Classifier: Programming Language :: Python :: Implementation :: PyPy
Classifier: Typing :: Typed
Requires-Dist: cryptography
